[
  {
    "jugador": "Yerai Montero Cabrera",
    "equipo": "DESAFÍO FS",
    "goles": 0
  },
  {
    "jugador": "YASSINE",
    "equipo": "NEXUS FS ",
    "goles": 0
  },
  {
    "jugador": "Victor Duque",
    "equipo": "DESAFÍO FS",
    "goles": 0
  },
  {
    "jugador": "TAREK",
    "equipo": "NEXUS FS ",
    "goles": 0
  },
  {
    "jugador": "Sergio Garcia",
    "equipo": "LOS FOGONES FS",
    "goles": 0
  },
  {
    "jugador": "SALVADOR GRAS RODRIGUEZ",
    "equipo": "TALLERES QUIMUR/FIDIASPRO",
    "goles": 0
  },
  {
    "jugador": "RAUL",
    "equipo": "NEXUS FS ",
    "goles": 0
  },
  {
    "jugador": "RAFIK",
    "equipo": "NEXUS FS ",
    "goles": 0
  },
  {
    "jugador": "PEDRO CANO GILABERT",
    "equipo": "NIEBLA LETAL FS",
    "goles": 0
  },
  {
    "jugador": "PABLO LEMA BELMONTE",
    "equipo": "NIEBLA LETAL FS",
    "goles": 0
  },
  {
    "jugador": "Oliver Rojas",
    "equipo": "DESAFÍO FS",
    "goles": 0
  },
  {
    "jugador": "OSWALDO",
    "equipo": "NEXUS FS ",
    "goles": 0
  },
  {
    "jugador": "OSCAR BUENDIA CUTILLAS",
    "equipo": "ASTON BIRRA FS",
    "goles": 0
  },
  {
    "jugador": "Mario quinto",
    "equipo": "LOS FOGONES FS",
    "goles": 0
  },
  {
    "jugador": "Manuel Vicente cayuchas",
    "equipo": "LOS FOGONES FS",
    "goles": 0
  },
  {
    "jugador": "Manuel Granda Velasquez",
    "equipo": "DESAFÍO FS",
    "goles": 0
  },
  {
    "jugador": "MOHAMED",
    "equipo": "NEXUS FS ",
    "goles": 0
  },
  {
    "jugador": "MIGUEL QUINTO RUIZ",
    "equipo": "ASTON BIRRA FS",
    "goles": 0
  },
  {
    "jugador": "MANUEL MARIN MURIES",
    "equipo": "NEXUS FS ",
    "goles": 0
  },
  {
    "jugador": "MANUEL JOSE MARTINEZ SERNA",
    "equipo": "ASTON BIRRA FS",
    "goles": 0
  },
  {
    "jugador": "MANUEL ALEJANDRO BERNÁ LOPEZ",
    "equipo": "ASTON BIRRA FS",
    "goles": 0
  },
  {
    "jugador": "Luis Ospino",
    "equipo": "DESAFÍO FS",
    "goles": 0
  },
  {
    "jugador": "Lledo",
    "equipo": "LOS FOGONES FS",
    "goles": 0
  },
  {
    "jugador": "LUIS BLASCO CLEMENTE",
    "equipo": "TALLERES QUIMUR/FIDIASPRO",
    "goles": 0
  },
  {
    "jugador": "Keiver H",
    "equipo": "DESAFÍO FS",
    "goles": 0
  },
  {
    "jugador": "KEVIN RODRIGUEZ CASTRO",
    "equipo": "NIEBLA LETAL FS",
    "goles": 0
  },
  {
    "jugador": "Juan Pedro Bema",
    "equipo": "LOS FOGONES FS",
    "goles": 0
  },
  {
    "jugador": "José Hernández",
    "equipo": "DESAFÍO FS",
    "goles": 0
  },
  {
    "jugador": "Josan",
    "equipo": "LOS FOGONES FS",
    "goles": 0
  },
  {
    "jugador": "Jestis Placido",
    "equipo": "LOS FOGONES FS",
    "goles": 0
  },
  {
    "jugador": "Jean Carlos Niño",
    "equipo": "DESAFÍO FS",
    "goles": 0
  },
  {
    "jugador": "Jack Joseph Andrés",
    "equipo": "LOS FOGONES FS",
    "goles": 0
  },
  {
    "jugador": "JUAN LUIS GUTIERREZ FUENTES",
    "equipo": "ASTON BIRRA FS",
    "goles": 0
  },
  {
    "jugador": "JUAN JOSE MARTINEZ GUILLEN",
    "equipo": "ASTON BIRRA FS",
    "goles": 0
  },
  {
    "jugador": "JOSE PASCUAL LOPEZ SERNA",
    "equipo": "ASTON BIRRA FS",
    "goles": 0
  },
  {
    "jugador": "JOSE MANUEL FERNANDEZ FERNANDEZ",
    "equipo": "NIEBLA LETAL FS",
    "goles": 0
  },
  {
    "jugador": "JOSE ANTONIO CORTES CALERO",
    "equipo": "NIEBLA LETAL FS",
    "goles": 0
  },
  {
    "jugador": "JONATAN GARCIA ALMARCHA",
    "equipo": "ASTON BIRRA FS",
    "goles": 0
  },
  {
    "jugador": "JOAQUIN GARCIA COSTA",
    "equipo": "TALLERES QUIMUR/FIDIASPRO",
    "goles": 0
  },
  {
    "jugador": "JAVIER LILLO LIMORTE ",
    "equipo": "NEXUS FS ",
    "goles": 0
  },
  {
    "jugador": "JAIME LIZÁN BERNÁ",
    "equipo": "ASTON BIRRA FS",
    "goles": 0
  },
  {
    "jugador": "ISRAEL CARTAGENA SUAREZ",
    "equipo": "TALLERES QUIMUR/FIDIASPRO",
    "goles": 0
  },
  {
    "jugador": "IKER SÁNCHEZ",
    "equipo": "NEXUS FS ",
    "goles": 0
  },
  {
    "jugador": "Francisco Javier Baeza",
    "equipo": "LOS FOGONES FS",
    "goles": 0
  },
  {
    "jugador": "FADEL",
    "equipo": "NEXUS FS ",
    "goles": 0
  },
  {
    "jugador": "Eloy Castillo González",
    "equipo": "DESAFÍO FS",
    "goles": 0
  },
  {
    "jugador": "Deivis Garaban",
    "equipo": "DESAFÍO FS",
    "goles": 0
  },
  {
    "jugador": "Darwin Arellano",
    "equipo": "DESAFÍO FS",
    "goles": 0
  },
  {
    "jugador": "Daniel Rocamora",
    "equipo": "LOS FOGONES FS",
    "goles": 0
  },
  {
    "jugador": "DANUEL PALACIOS ALBIÑANA",
    "equipo": "NIEBLA LETAL FS",
    "goles": 0
  },
  {
    "jugador": "DANIEL LIMORTE RODES",
    "equipo": "ASTON BIRRA FS",
    "goles": 0
  },
  {
    "jugador": "DANIEL",
    "equipo": "NEXUS FS ",
    "goles": 0
  },
  {
    "jugador": "Carlos Hernandez",
    "equipo": "DESAFÍO FS",
    "goles": 0
  },
  {
    "jugador": "CRISTIAN SANCHEZ CASTRO",
    "equipo": "NEXUS FS ",
    "goles": 0
  },
  {
    "jugador": "BRYAN RODRÍGUEZ CASTRO",
    "equipo": "NIEBLA LETAL FS",
    "goles": 0
  },
  {
    "jugador": "BRYAN",
    "equipo": "NEXUS FS ",
    "goles": 0
  },
  {
    "jugador": "Alejandro Parada",
    "equipo": "DESAFÍO FS",
    "goles": 0
  },
  {
    "jugador": "Alejandro Martinez Sema",
    "equipo": "LOS FOGONES FS",
    "goles": 0
  },
  {
    "jugador": "Alejandro Hermando",
    "equipo": "LOS FOGONES FS",
    "goles": 0
  },
  {
    "jugador": "Alejandro Gomez",
    "equipo": "LOS FOGONES FS",
    "goles": 0
  },
  {
    "jugador": "Alberth Sanchez",
    "equipo": "DESAFÍO FS",
    "goles": 0
  },
  {
    "jugador": "Adrian",
    "equipo": "LOS FOGONES FS",
    "goles": 0
  },
  {
    "jugador": "ALEXANDER LOPEZ LOZANO",
    "equipo": "TALLERES QUIMUR/FIDIASPRO",
    "goles": 0
  },
  {
    "jugador": "A.FADEL",
    "equipo": "NEXUS FS ",
    "goles": 0
  },
  {
    "jugador": " JUAN CARLOS BORDONADO LOPEZ",
    "equipo": "TALLERES QUIMUR/FIDIASPRO",
    "goles": 0
  },
  {
    "jugador": " JUAN ANTONIO FRESNEDA FERRER",
    "equipo": "TALLERES QUIMUR/FIDIASPRO",
    "goles": 0
  },
  {
    "jugador": " JOSE JOAQUIN SAEZ PATIÑO",
    "equipo": "TALLERES QUIMUR/FIDIASPRO",
    "goles": 0
  },
  {
    "jugador": " JOAN PEREZ MARTI",
    "equipo": "TALLERES QUIMUR/FIDIASPRO",
    "goles": 0
  },
  {
    "jugador": "  GERMAN MORALES TIMONER",
    "equipo": "TALLERES QUIMUR/FIDIASPRO",
    "goles": 0
  },
  {
    "jugador": "  ENRIQUE GARCIA PEDRERO ",
    "equipo": "TALLERES QUIMUR/FIDIASPRO",
    "goles": 0
  },
  {
    "jugador": "  CRISTIAN MORALES GONZALEZ ",
    "equipo": "TALLERES QUIMUR/FIDIASPRO",
    "goles": 0
  }
]